data_golf/__init__.py
data_golf/api/__init__.py
data_golf/api/betting.py
data_golf/api/general.py
data_golf/api/historical.py
data_golf/api/live_prediction.py
data_golf/api/prediction.py
data_golf/client.py
data_golf/config.py
data_golf/http_client.py
data_golf/request_helpers.py
data_golf-0.5.1.dist-info/LICENSE
data_golf-0.5.1.dist-info/METADATA
data_golf-0.5.1.dist-info/WHEEL
data_golf-0.5.1.dist-info/RECORD
