Metadata-Version: 2.1
Name: data_golf
Version: 0.5.1
Summary: API Wrapper for DataGolf.com endpoints.
Home-page: https://github.com/coreyjs/data-golf-api
License: MIT
Keywords: golf,datagolf,data golf,golf data,golf AI,golf machine learning,golf ML,golf stats
Author: Corey Schaf
Author-email: cschaf@gmail.com
Requires-Python: >=3.9,<4.0
Classifier: Development Status :: 4 - Beta
Classifier: Intended Audience :: Developers
Classifier: License :: OSI Approved :: MIT License
Classifier: Programming Language :: Python
Classifier: Programming Language :: Python :: 3
Classifier: Programming Language :: Python :: 3.9
Classifier: Programming Language :: Python :: 3.10
Classifier: Programming Language :: Python :: 3.11
Classifier: Programming Language :: Python :: 3.12
Classifier: Topic :: Software Development :: Libraries
Classifier: Topic :: Software Development :: Libraries :: Python Modules
Requires-Dist: httpx (>=0.27.0,<0.28.0)
Project-URL: Repository, https://github.com/coreyjs/data-golf-api
